openbankingapi/__init__.py
openbankingapi/api.py
openbankingapi/resources/quovadis.pem
openbankingapi-0.1.5.post1.dist-info/LICENSE
openbankingapi-0.1.5.post1.dist-info/METADATA
openbankingapi-0.1.5.post1.dist-info/WHEEL
openbankingapi-0.1.5.post1.dist-info/top_level.txt
openbankingapi-0.1.5.post1.dist-info/RECORD
