Metadata-Version: 2.1
Name: openbankingapi
Version: 0.1.5.post1
Summary: Simple wrapper for openbanking
Home-page: https://github.com/FundingOptions/openbanking-api
Author: Funding Options
Author-email: techsupport@fundingoptions.com
License: GPLv3
Platform: UNKNOWN
Requires-Dist: requests
